<?xml version="1.0" encoding="UTF-8" standalone="yes"?>
<APIProxy revision="2" name="CORS-Enb">
    <Basepaths>/cors-enb</Basepaths>
    <ConfigurationVersion majorVersion="4" minorVersion="0"/>
    <CreatedAt>1575857663723</CreatedAt>
    <CreatedBy>verma.govind92@gmail.com</CreatedBy>
    <Description></Description>
    <DisplayName>CORS-Enb</DisplayName>
    <LastModifiedAt>1575857663723</LastModifiedAt>
    <LastModifiedBy>verma.govind92@gmail.com</LastModifiedBy>
    <ManifestVersion>SHA-512:5e8e36caafd90433198974952d7be254ccb46cc40fc6a1da6c9a08dd276ee9e3359df6c82be77ac70ee3b1661783bd7239fb71cacbf393aeee65904c60461ae7</ManifestVersion>
    <Policies>
        <Policy>add-cors</Policy>
    </Policies>
    <ProxyEndpoints>
        <ProxyEndpoint>default</ProxyEndpoint>
    </ProxyEndpoints>
    <Resources/>
    <Spec></Spec>
    <TargetServers/>
    <TargetEndpoints>
        <TargetEndpoint>default</TargetEndpoint>
    </TargetEndpoints>
</APIProxy>
